README.md
setup.py
scrapyx_scraperapi/__init__.py
scrapyx_scraperapi/scraperapi.py
scrapyx_scraperapi_proxy.egg-info/PKG-INFO
scrapyx_scraperapi_proxy.egg-info/SOURCES.txt
scrapyx_scraperapi_proxy.egg-info/dependency_links.txt
scrapyx_scraperapi_proxy.egg-info/requires.txt
scrapyx_scraperapi_proxy.egg-info/top_level.txt