Metadata-Version: 1.2
Name: scrapyx-scraperapi-proxy
Version: 0.1.1
Summary: Scrapy scraperapi Proxy: scraperapi interfacing middleware for Scrapy
Home-page: https://github.com/tubndgit/scrapyx-scraperapi-proxy
Author: Henry B.
Author-email: tubnd.younet@gmail.com
License: MIT
Download-URL: https://github.com/tubndgit/scrapyx-scraperapi-proxy/archive/master.zip
Platform: UNKNOWN
Requires-Python: >=3.6
